Metadata-Version: 1.1
Name: TableDraw
Version: 0.2
Summary: lib for table drawing
Home-page: https://github.com/AlexOdlin/TableDraw
Author: Sokolov Alex, Babaev George
Author-email: sva193@yahoo.com, online_vb@mail.ru
License: UNKNOWN
Download-URL: https://github.com/AlexOdlin/TableDraw/archive/0.2.tar.gz
Keywords: table,drawing
Platform: UNKNOWN
